<annotation>
	<folder>new_img</folder>
	<filename>new_image19.png</filename>
	<path>C:\Users\kevin\Desktop\new_img\new_image19.png</path>
	<source>
		<database>Unknown</database>
	</source>
	<size>
		<width>400</width>
		<height>400</height>
		<depth>3</depth>
	</size>
	<segmented>0</segmented>
	<object>
		<name>hpbar</name>
		<pose>Unspecified</pose>
		<truncated>0</truncated>
		<difficult>0</difficult>
		<bndbox>
			<xmin>45</xmin>
			<ymin>99</ymin>
			<xmax>160</xmax>
			<ymax>108</ymax>
		</bndbox>
	</object>
	<object>
		<name>hpbar</name>
		<pose>Unspecified</pose>
		<truncated>0</truncated>
		<difficult>0</difficult>
		<bndbox>
			<xmin>247</xmin>
			<ymin>128</ymin>
			<xmax>362</xmax>
			<ymax>138</ymax>
		</bndbox>
	</object>
</annotation>
